optiml_flow/__init__.py
optiml_flow/optiml_flow.py
optiml_flow-0.1.0.dist-info/METADATA
optiml_flow-0.1.0.dist-info/WHEEL
optiml_flow-0.1.0.dist-info/top_level.txt
optiml_flow-0.1.0.dist-info/RECORD
